pygeems/__init__.py
pygeems/dyn_props.py
pygeems/ground_motion.py
pygeems/site_invest.py
pygeems/slope_disp.py
pygeems/utils.py
tests/__init__.py
tests/test_dyn_props.py
tests/test_ground_motion.py
tests/test_site_invest.py
tests/test_slope_disp.py
pyGEEMs-0.2.1.dist-info/LICENSE
pyGEEMs-0.2.1.dist-info/METADATA
pyGEEMs-0.2.1.dist-info/WHEEL
pyGEEMs-0.2.1.dist-info/top_level.txt
pyGEEMs-0.2.1.dist-info/RECORD
