Metadata-Version: 2.1
Name: pyGEEMs
Version: 0.2.1
Summary: Geotechnical earthquake engineering models implemented in Python.
Home-page: http://github.com/arkottke/pygeems
Author: Albert Kottke
Author-email: albert.kottke@gmail.com
License: MIT
Platform: UNKNOWN
Classifier: License :: OSI Approved :: MIT License
Classifier: Environment :: Console
Classifier: Natural Language :: English
Classifier: Operating System :: OS Independent
Classifier: Programming Language :: Python :: 3.8
Classifier: Programming Language :: Python
Classifier: Topic :: Scientific/Engineering
Classifier: Intended Audience :: Science/Research
Requires-Dist: numpy
Requires-Dist: numba
Requires-Dist: setuptools
Requires-Dist: scipy
